optimisticadmin/__init__.py
optimisticadmin/expressions.py
optimisticadmin/mixins.py
django_optimistic_admin_pg-1.0.0.dist-info/LICENSE
django_optimistic_admin_pg-1.0.0.dist-info/METADATA
django_optimistic_admin_pg-1.0.0.dist-info/WHEEL
django_optimistic_admin_pg-1.0.0.dist-info/top_level.txt
django_optimistic_admin_pg-1.0.0.dist-info/RECORD
