Metadata-Version: 2.1
Name: django-optimistic-admin-pg
Version: 1.0.0
Summary: django-optimistic-admin-pg providing mixins for implementing optimistic concurrency in Django using PostgreSQL
Home-page: https://github.com/djungle-io/django-optimistic-admin-pg
Author: Riccardo Magliocchetti
Author-email: riccardo.magliocchetti@gmail.com
Maintainer: Djungle Studio
Maintainer-email: tech@djungle.io
License: MIT License
Keywords: django,admin,concurrency,postgresql
Platform: UNKNOWN
Classifier: Development Status :: 5 - Production/Stable
Classifier: Environment :: Web Environment
Classifier: Framework :: Django
Classifier: Framework :: Django :: 3.2
Classifier: Framework :: Django :: 4.0
Classifier: Intended Audience :: Developers
Classifier: License :: OSI Approved :: MIT License
Classifier: Operating System :: OS Independent
Classifier: Programming Language :: Python
Classifier: Programming Language :: Python :: 3
Classifier: Programming Language :: Python :: 3.6
Classifier: Programming Language :: Python :: 3.7
Classifier: Programming Language :: Python :: 3.8
Classifier: Programming Language :: Python :: 3.9
Classifier: Programming Language :: Python :: 3.10
Classifier: Topic :: Software Development :: Libraries :: Application Frameworks
Classifier: Topic :: Software Development :: Libraries :: Python Modules
License-File: LICENSE
Requires-Dist: Django (>=3.2)
